Metadata-Version: 2.1
Name: odoo14-addon-ssi_odoo_implementation_data_requirement
Version: 14.0.1.0.1.dev1
Summary: Odoo Implementation - Data Requirement Integration
Home-page: https://simetri-sinergi.id
Author: OpenSynergy Indonesia, PT. Simetri Sinergi Indonesia
License: AGPL-3
Classifier: Programming Language :: Python
Classifier: Framework :: Odoo
Classifier: Framework :: Odoo :: 14.0
Classifier: License :: OSI Approved :: GNU Affero General Public License v3
Requires-Python: >=3.6
Requires-Dist: odoo14-addon-ssi-data-requirement-mixin
Requires-Dist: odoo14-addon-ssi-odoo-implementation
Requires-Dist: odoo<14.1dev,>=14.0a
